pngminifier/__main__.py
pngminifier/_pngc.py
pngminifier-1.0.4.dist-info/LICENSE.md
pngminifier-1.0.4.dist-info/METADATA
pngminifier-1.0.4.dist-info/WHEEL
pngminifier-1.0.4.dist-info/entry_points.txt
pngminifier-1.0.4.dist-info/top_level.txt
pngminifier-1.0.4.dist-info/RECORD
