Metadata-Version: 2.1
Name: pngminifier
Version: 1.0.4
Summary: a program that strips out ancillary data from PNG files and reduces the file slightly
Home-page: UNKNOWN
Author: Shantanu Biswas
Author-email: bsantanu381@gmail.com
License: The Unlicense
Project-URL: Github, https://github.com/tripulse/pngminifier
Keywords: png,minifier,minification,truncatorexif tag remover,pngminify
Platform: UNKNOWN
Requires-Python: >=3.8
